MANIFEST.in
README.rst
TITLE.txt
lh-agpl3-LICENSE.txt
setup.py
unisos/__init__.py
unisos.ucf.egg-info/PKG-INFO
unisos.ucf.egg-info/SOURCES.txt
unisos.ucf.egg-info/dependency_links.txt
unisos.ucf.egg-info/namespace_packages.txt
unisos.ucf.egg-info/not-zip-safe
unisos.ucf.egg-info/top_level.txt
unisos/ucf/__init__.py
unisos/ucf/ucf.py