Metadata-Version: 1.1
Name: unisos.ucf
Version: 0.11
Summary: UCF Library: Unisos Common Functions/Facilities -- A collection of common functions that are primarily used by ICMs.
